pam/__init__.py
pam/aql.py
pam/client.py
pam/collection.py
pam/converter.py
pam/database.py
pam/utils.py
python_arango_mapper-0.1.8.dist-info/LICENSE
python_arango_mapper-0.1.8.dist-info/METADATA
python_arango_mapper-0.1.8.dist-info/WHEEL
python_arango_mapper-0.1.8.dist-info/top_level.txt
python_arango_mapper-0.1.8.dist-info/RECORD
