Metadata-Version: 2.1
Name: python-arango-mapper
Version: 0.1.8
Summary: fast and easy-to-use python-arango mapper library
Home-page: https://github.com/ud803/python-arango-mapper
Author: lee ui dam
Author-email: ud803da@gmail.com
License: GNU General Public License v3.0
Platform: UNKNOWN
Requires-Python: >=3.7
License-File: LICENSE
Requires-Dist: certifi (==2021.10.8)
Requires-Dist: charset-normalizer (==2.0.12)
Requires-Dist: idna (==3.3)
Requires-Dist: packaging (==21.3)
Requires-Dist: PyJWT (==2.3.0)
Requires-Dist: pyparsing (==3.0.7)
Requires-Dist: python-arango (==7.3.1)
Requires-Dist: requests (==2.27.1)
Requires-Dist: requests-toolbelt (==0.9.1)
Requires-Dist: setuptools-scm (==6.4.2)
Requires-Dist: tomli (==2.0.1)
Requires-Dist: urllib3 (==1.26.9)
